[
  {
    "avatar": "https://ca.slack-edge.com/T03UH1KU06L-U03U7U12SN8-d08629b08ca1-512",
    "name": "Mango",
    "isOnline": true,
    "id": 1812
  },
  {
    "avatar": "https://ca.slack-edge.com/T03UH1KU06L-U03UV1UDDFS-8c25e72ff647-512",
    "name": "Kiwi",
    "isOnline": false,
    "id": 1137
  },
  {
    "avatar": "https://ca.slack-edge.com/T03UH1KU06L-U03TYLK25L6-3d832a5915e8-512",
    "name": "Ajax",
    "isOnline": true,
    "id": 1213
  },
  {
    "avatar": "https://ca.slack-edge.com/T03UH1KU06L-U03TYSCGAR4-dc6dfed72e30-512",
    "name": "Jay",
    "isOnline": true,
    "id": 1714
  },
  {
    "avatar": "https://ca.slack-edge.com/T03UH1KU06L-U03TYNMAFQE-896ae3d96e50-512",
    "name": "Poly",
    "isOnline": false,
    "id": 1284
  }
]
